impasse/__init__.py
impasse/constants.py
impasse/core.py
impasse/errors.py
impasse/helper.py
impasse/structs.py
impasse/structs_base.py
impasse-5.4.2.data/data/share/impasse/README.md
impasse-5.4.2.dist-info/licenses/LICENSE
impasse-5.4.2.dist-info/METADATA
impasse-5.4.2.dist-info/WHEEL
impasse-5.4.2.dist-info/top_level.txt
impasse-5.4.2.dist-info/RECORD
