Metadata-Version: 2.4
Name: impasse
Version: 5.4.2
Summary: Alternate Python bindings for the Open Asset Import Library (ASSIMP)
Home-page: https://github.com/SaladDais/Impasse
Author: Salad Dais
Author-email: SaladDais@users.noreply.github.com
License: BSD
Requires-Python: >=3.7
License-File: LICENSE
Requires-Dist: numpy
Requires-Dist: cffi
Dynamic: author
Dynamic: author-email
Dynamic: description
Dynamic: description-content-type
Dynamic: home-page
Dynamic: license
Dynamic: license-file
Dynamic: requires-dist
Dynamic: requires-python
Dynamic: summary
